defectdojo_cli2/Announcements.py
defectdojo_cli2/ApiToken.py
defectdojo_cli2/EnvDefaults.py
defectdojo_cli2/ImportLanguages.py
defectdojo_cli2/ReImportScan.py
defectdojo_cli2/__init__.py
defectdojo_cli2/__main__.py
defectdojo_cli2/engagements.py
defectdojo_cli2/findings.py
defectdojo_cli2/tests.py
defectdojo_cli2/util.py
defectdojo_cli2-0.1.15.dist-info/AUTHORS
defectdojo_cli2-0.1.15.dist-info/LICENSE
defectdojo_cli2-0.1.15.dist-info/METADATA
defectdojo_cli2-0.1.15.dist-info/WHEEL
defectdojo_cli2-0.1.15.dist-info/entry_points.txt
defectdojo_cli2-0.1.15.dist-info/RECORD
