Metadata-Version: 2.1
Name: defectdojo-cli2
Version: 0.1.15
Summary: CLI Wrapper for DefectDojo using APIv2
License: MIT
Author: Mikke Schirén
Author-email: mikke.schiren@digitalist.com
Requires-Python: >=3.12,<4.0
Classifier: License :: OSI Approved :: MIT License
Classifier: Programming Language :: Python :: 3
Classifier: Programming Language :: Python :: 3.12
Requires-Dist: requests (>=2.32.3,<3.0.0)
Requires-Dist: rich-argparse (>=1.5.2,<2.0.0)
Requires-Dist: setuptools (>=75.0.0,<76.0.0)
Requires-Dist: tabulate (>=0.9.0,<0.10.0)
